setup.py
./__init__.py
./chaosrouter.py
chaosrouter.egg-info/PKG-INFO
chaosrouter.egg-info/SOURCES.txt
chaosrouter.egg-info/dependency_links.txt
chaosrouter.egg-info/requires.txt
chaosrouter.egg-info/top_level.txt