Metadata-Version: 1.1
Name: chaosrouter
Version: 0.2.6
Summary: Route path based requests to JSON endpoints.  Designed for web APIs
Home-page: https://github.com/webheroesinc/chaos-router
Author: Matthew Brisebois
Author-email: matthew@webheroes.ca
License: Dual License; GPLv3 and Proprietary
Platform: UNKNOWN
Classifier: License :: OSI Approved :: GNU General Public License v3 or later (GPLv3+)
Classifier: License :: Other/Proprietary License
Classifier: Programming Language :: Python :: 3.5
Classifier: Development Status :: 4 - Beta
Classifier: Intended Audience :: Developers
